cli/__init__.py
cli/alora/__init__.py
cli/alora/commands.py
cli/alora/train.py
cli/alora/upload.py
cli/decompose/README.md
cli/decompose/__init__.py
cli/decompose/decompose.py
cli/decompose/m_decomp_result_v1.py.jinja2
cli/decompose/pipeline.py
cli/decompose/prompt_modules/__init__.py
cli/decompose/prompt_modules/_prompt_modules.py
cli/decompose/prompt_modules/constraint_extractor/__init__.py
cli/decompose/prompt_modules/constraint_extractor/_constraint_extractor.py
cli/decompose/prompt_modules/constraint_extractor/_exceptions.py
cli/decompose/prompt_modules/constraint_extractor/_prompt/__init__.py
cli/decompose/prompt_modules/constraint_extractor/_prompt/_icl_examples/__init__.py
cli/decompose/prompt_modules/constraint_extractor/_prompt/_icl_examples/_example_1/__init__.py
cli/decompose/prompt_modules/constraint_extractor/_prompt/_icl_examples/_example_1/_example.py
cli/decompose/prompt_modules/constraint_extractor/_prompt/_icl_examples/_example_1/task_prompt.txt
cli/decompose/prompt_modules/constraint_extractor/_prompt/_icl_examples/_example_2/__init__.py
cli/decompose/prompt_modules/constraint_extractor/_prompt/_icl_examples/_example_2/_example.py
cli/decompose/prompt_modules/constraint_extractor/_prompt/_icl_examples/_example_2/task_prompt.txt
cli/decompose/prompt_modules/constraint_extractor/_prompt/_icl_examples/_example_3/__init__.py
cli/decompose/prompt_modules/constraint_extractor/_prompt/_icl_examples/_example_3/_example.py
cli/decompose/prompt_modules/constraint_extractor/_prompt/_icl_examples/_example_3/task_prompt.txt
cli/decompose/prompt_modules/constraint_extractor/_prompt/_icl_examples/_example_4/__init__.py
cli/decompose/prompt_modules/constraint_extractor/_prompt/_icl_examples/_example_4/_example.py
cli/decompose/prompt_modules/constraint_extractor/_prompt/_icl_examples/_example_4/task_prompt.txt
cli/decompose/prompt_modules/constraint_extractor/_prompt/_icl_examples/_example_5/__init__.py
mellea-0.2.4.dist-info/METADATA
mellea-0.2.4.dist-info/WHEEL
mellea-0.2.4.dist-info/entry_points.txt
mellea-0.2.4.dist-info/licenses/LICENSE
mellea-0.2.4.dist-info/RECORD
