Metadata-Version: 2.1
Name: mellea
Version: 0.2.4
Summary: mellea is a library for writing generative programs
Author-Email: Nathan Fulton <nathan@ibm.com>, Hendrik Strobelt <hendrik.strobelt@ibm.com>, Avinash Balakrishnan <avinash.bala@us.ibm.com>, Elron Bandel <elron.bandel@ibm.com>, Masataro Asai <masataro.asai@ibm.com>, Supriya Lall <supriya.lall@partner.ibm.com>, Xiaojie Guo <xiaojie.guo@ibm.com>, Jake LoRocco <jake.lorocco@ibm.com>, Ja Young Lee <Ja.Young.Lee@ibm.com>
Classifier: Programming Language :: Python :: 3
Classifier: License :: OSI Approved :: Apache Software License
Classifier: Operating System :: OS Independent
Requires-Python: >=3.10
Requires-Dist: pydantic
Requires-Dist: openai
Requires-Dist: jinja2
Requires-Dist: json5
Requires-Dist: ollama>=0.5.1
Requires-Dist: ansicolors
Requires-Dist: requests>=2.32.3
Requires-Dist: uvicorn
Requires-Dist: fastapi
Requires-Dist: types-requests
Requires-Dist: types-tqdm
Requires-Dist: typer
Requires-Dist: click<8.2.0
Requires-Dist: mistletoe>=1.4.0
Requires-Dist: huggingface-hub>=0.33.4
Requires-Dist: pillow
Requires-Dist: granite-common>=0.3.6
Requires-Dist: math_verify
Requires-Dist: rouge_score
Requires-Dist: llm-sandbox[docker]>=0.3.23
Provides-Extra: hf
Requires-Dist: accelerate>=1.9.0; extra == "hf"
Requires-Dist: alora==0.2.0; extra == "hf"
Requires-Dist: datasets>=4.0.0; extra == "hf"
Requires-Dist: outlines-core==0.1.26; extra == "hf"
Requires-Dist: outlines; extra == "hf"
Requires-Dist: peft>=0.18.0; extra == "hf"
Requires-Dist: transformers>=4.53.2; extra == "hf"
Requires-Dist: trl==0.19.1; extra == "hf"
Provides-Extra: vllm
Requires-Dist: transformers<4.54.0; extra == "vllm"
Requires-Dist: numpy<2.0.0; extra == "vllm"
Requires-Dist: outlines-core==0.1.26; extra == "vllm"
Requires-Dist: vllm>=0.9.1; extra == "vllm"
Provides-Extra: litellm
Requires-Dist: litellm>=1.76; extra == "litellm"
Provides-Extra: watsonx
Requires-Dist: ibm-watsonx-ai>=1.3.31; extra == "watsonx"
Provides-Extra: docling
Requires-Dist: docling>=2.45.0; extra == "docling"
Provides-Extra: all
Requires-Dist: mellea[docling,hf,litellm,vllm,watsonx]; extra == "all"
